{
  "services": [
    {
      "name": "cloudflare",
      "displayName": "Cloudflare",
      "status": "degraded",
      "description": "Minor Service Outage",
      "lastChecked": "2025-12-08T21:13:14.642Z"
    },
    {
      "name": "azure",
      "displayName": "Azure Services",
      "status": "outage",
      "description": "Major incident affecting multiple services",
      "lastChecked": "2025-12-08T21:13:15.658Z"
    },
    {
      "name": "confluent",
      "displayName": "Confluent Cloud",
      "status": "degraded",
      "description": "Partially Degraded Service",
      "lastChecked": "2025-12-08T21:13:18.957Z"
    },
    {
      "name": "nylas",
      "displayName": "Nylas",
      "status": "operational",
      "description": "No active incidents detected",
      "lastChecked": "2025-12-08T21:13:14.641Z"
    },
    {
      "name": "sendgrid",
      "displayName": "SendGrid",
      "status": "operational",
      "description": "All Systems Operational",
      "lastChecked": "2025-12-08T21:13:14.694Z"
    },
    {
      "name": "twilio",
      "displayName": "Twilio Communications",
      "status": "degraded",
      "description": "Partially Degraded Service",
      "lastChecked": "2025-12-08T21:13:14.713Z"
    },
    {
      "name": "postmark",
      "displayName": "Postmark",
      "status": "operational",
      "description": "All systems operational",
      "lastChecked": "2025-12-08T21:13:14.816Z"
    },
    {
      "name": "zohomail",
      "displayName": "Zoho Mail",
      "status": "operational",
      "description": "All systems operational",
      "lastChecked": "2025-12-08T21:13:15.975Z"
    },
    {
      "name": "mailgun",
      "displayName": "Mailgun",
      "status": "operational",
      "description": "All Systems Operational",
      "lastChecked": "2025-12-08T21:13:14.807Z"
    }
  ],
  "lastUpdated": "2025-12-08T21:13:18.957Z",
  "overallStatus": "outage"
}