{
  "services": [
    {
      "name": "cloudflare",
      "displayName": "Cloudflare",
      "status": "degraded",
      "description": "Minor Service Outage",
      "lastChecked": "2025-12-17T06:59:22.486Z"
    },
    {
      "name": "azure",
      "displayName": "Azure Services",
      "status": "outage",
      "description": "Major incident affecting multiple services",
      "lastChecked": "2025-12-17T06:59:23.538Z"
    },
    {
      "name": "confluent",
      "displayName": "Confluent Cloud",
      "status": "operational",
      "description": "All Systems Operational",
      "lastChecked": "2025-12-17T06:59:22.488Z"
    },
    {
      "name": "nylas",
      "displayName": "Nylas",
      "status": "operational",
      "description": "No active incidents detected",
      "lastChecked": "2025-12-17T06:59:22.484Z"
    },
    {
      "name": "sendgrid",
      "displayName": "SendGrid",
      "status": "operational",
      "description": "All Systems Operational",
      "lastChecked": "2025-12-17T06:59:22.487Z"
    },
    {
      "name": "twilio",
      "displayName": "Twilio Communications",
      "status": "unknown",
      "description": "Service Under Maintenance",
      "lastChecked": "2025-12-17T06:59:22.503Z"
    },
    {
      "name": "postmark",
      "displayName": "Postmark",
      "status": "operational",
      "description": "All systems operational",
      "lastChecked": "2025-12-17T06:59:23.546Z"
    },
    {
      "name": "zohomail",
      "displayName": "Zoho Mail",
      "status": "operational",
      "description": "All systems operational",
      "lastChecked": "2025-12-17T06:59:24.002Z"
    },
    {
      "name": "mailgun",
      "displayName": "Mailgun",
      "status": "operational",
      "description": "All Systems Operational",
      "lastChecked": "2025-12-17T06:59:22.763Z"
    }
  ],
  "lastUpdated": "2025-12-17T06:59:24.002Z",
  "overallStatus": "outage"
}