{
  "services": [
    {
      "name": "cloudflare",
      "displayName": "Cloudflare",
      "status": "degraded",
      "description": "Minor Service Outage",
      "lastChecked": "2026-01-01T09:34:27.955Z"
    },
    {
      "name": "azure",
      "displayName": "Azure Services",
      "status": "outage",
      "description": "Major incident affecting multiple services",
      "lastChecked": "2026-01-01T09:34:29.362Z"
    },
    {
      "name": "confluent",
      "displayName": "Confluent Cloud",
      "status": "operational",
      "description": "All Systems Operational",
      "lastChecked": "2026-01-01T09:34:27.821Z"
    },
    {
      "name": "nylas",
      "displayName": "Nylas",
      "status": "operational",
      "description": "No active incidents detected",
      "lastChecked": "2026-01-01T09:34:27.953Z"
    },
    {
      "name": "sendgrid",
      "displayName": "SendGrid",
      "status": "operational",
      "description": "All Systems Operational",
      "lastChecked": "2026-01-01T09:34:28.047Z"
    },
    {
      "name": "twilio",
      "displayName": "Twilio Communications",
      "status": "degraded",
      "description": "Partially Degraded Service",
      "lastChecked": "2026-01-01T09:34:28.040Z"
    },
    {
      "name": "postmark",
      "displayName": "Postmark",
      "status": "operational",
      "description": "All systems operational",
      "lastChecked": "2026-01-01T09:34:28.196Z"
    },
    {
      "name": "zohomail",
      "displayName": "Zoho Mail",
      "status": "operational",
      "description": "All systems operational",
      "lastChecked": "2026-01-01T09:34:29.671Z"
    },
    {
      "name": "mailgun",
      "displayName": "Mailgun",
      "status": "operational",
      "description": "All Systems Operational",
      "lastChecked": "2026-01-01T09:34:28.283Z"
    }
  ],
  "lastUpdated": "2026-01-01T09:34:29.671Z",
  "overallStatus": "outage"
}