{
  "services": [
    {
      "name": "cloudflare",
      "displayName": "Cloudflare",
      "status": "degraded",
      "description": "Minor Service Outage",
      "lastChecked": "2025-12-13T13:40:22.679Z"
    },
    {
      "name": "azure",
      "displayName": "Azure Services",
      "status": "outage",
      "description": "Major incident affecting multiple services",
      "lastChecked": "2025-12-13T13:40:24.124Z"
    },
    {
      "name": "confluent",
      "displayName": "Confluent Cloud",
      "status": "operational",
      "description": "All Systems Operational",
      "lastChecked": "2025-12-13T13:40:22.856Z"
    },
    {
      "name": "nylas",
      "displayName": "Nylas",
      "status": "operational",
      "description": "No active incidents detected",
      "lastChecked": "2025-12-13T13:40:22.853Z"
    },
    {
      "name": "sendgrid",
      "displayName": "SendGrid",
      "status": "operational",
      "description": "All Systems Operational",
      "lastChecked": "2025-12-13T13:40:22.864Z"
    },
    {
      "name": "twilio",
      "displayName": "Twilio Communications",
      "status": "degraded",
      "description": "Partially Degraded Service",
      "lastChecked": "2025-12-13T13:40:22.940Z"
    },
    {
      "name": "postmark",
      "displayName": "Postmark",
      "status": "operational",
      "description": "All systems operational",
      "lastChecked": "2025-12-13T13:40:22.963Z"
    },
    {
      "name": "zohomail",
      "displayName": "Zoho Mail",
      "status": "operational",
      "description": "All systems operational",
      "lastChecked": "2025-12-13T13:40:24.347Z"
    },
    {
      "name": "mailgun",
      "displayName": "Mailgun",
      "status": "operational",
      "description": "All Systems Operational",
      "lastChecked": "2025-12-13T13:40:23.156Z"
    }
  ],
  "lastUpdated": "2025-12-13T13:40:24.347Z",
  "overallStatus": "outage"
}