{
  "services": [
    {
      "name": "cloudflare",
      "displayName": "Cloudflare",
      "status": "degraded",
      "description": "Minor Service Outage",
      "lastChecked": "2026-06-08T11:59:31.816Z"
    },
    {
      "name": "azure",
      "displayName": "Azure Services",
      "status": "outage",
      "description": "Major incident affecting multiple services",
      "lastChecked": "2026-06-08T11:59:33.076Z"
    },
    {
      "name": "confluent",
      "displayName": "Confluent Cloud",
      "status": "operational",
      "description": "All Systems Operational",
      "lastChecked": "2026-06-08T11:59:31.885Z"
    },
    {
      "name": "nylas",
      "displayName": "Nylas",
      "status": "operational",
      "description": "No active incidents detected",
      "lastChecked": "2026-06-08T11:59:32.061Z"
    },
    {
      "name": "sendgrid",
      "displayName": "SendGrid",
      "status": "operational",
      "description": "All Systems Operational",
      "lastChecked": "2026-06-08T11:59:31.951Z"
    },
    {
      "name": "twilio",
      "displayName": "Twilio Communications",
      "status": "degraded",
      "description": "Partially Degraded Service",
      "lastChecked": "2026-06-08T11:59:32.062Z"
    },
    {
      "name": "postmark",
      "displayName": "Postmark",
      "status": "operational",
      "description": "All systems operational",
      "lastChecked": "2026-06-08T11:59:33.082Z"
    },
    {
      "name": "zohomail",
      "displayName": "Zoho Mail",
      "status": "operational",
      "description": "All systems operational",
      "lastChecked": "2026-06-08T11:59:33.618Z"
    },
    {
      "name": "mailgun",
      "displayName": "Mailgun",
      "status": "operational",
      "description": "All Systems Operational",
      "lastChecked": "2026-06-08T11:59:32.164Z"
    }
  ],
  "lastUpdated": "2026-06-08T11:59:33.618Z",
  "overallStatus": "outage"
}