{
  "services": [
    {
      "name": "cloudflare",
      "displayName": "Cloudflare",
      "status": "degraded",
      "description": "Minor Service Outage",
      "lastChecked": "2025-09-22T19:55:35.517Z"
    },
    {
      "name": "azure",
      "displayName": "Azure Services",
      "status": "outage",
      "description": "Major incident affecting multiple services",
      "lastChecked": "2025-09-22T19:55:36.977Z"
    },
    {
      "name": "confluent",
      "displayName": "Confluent Cloud",
      "status": "operational",
      "description": "All Systems Operational",
      "lastChecked": "2025-09-22T19:55:35.544Z"
    },
    {
      "name": "nylas",
      "displayName": "Nylas",
      "status": "operational",
      "description": "No active incidents detected",
      "lastChecked": "2025-09-22T19:55:35.709Z"
    },
    {
      "name": "sendgrid",
      "displayName": "SendGrid",
      "status": "degraded",
      "description": "Partially Degraded Service",
      "lastChecked": "2025-09-22T19:55:35.584Z"
    },
    {
      "name": "twilio",
      "displayName": "Twilio Communications",
      "status": "unknown",
      "description": "Service Under Maintenance",
      "lastChecked": "2025-09-22T19:55:35.711Z"
    },
    {
      "name": "postmark",
      "displayName": "Postmark",
      "status": "operational",
      "description": "All systems operational",
      "lastChecked": "2025-09-22T19:55:35.817Z"
    },
    {
      "name": "zohomail",
      "displayName": "Zoho Mail",
      "status": "operational",
      "description": "All systems operational",
      "lastChecked": "2025-09-22T19:55:37.179Z"
    },
    {
      "name": "mailgun",
      "displayName": "Mailgun",
      "status": "operational",
      "description": "All Systems Operational",
      "lastChecked": "2025-09-22T19:55:35.956Z"
    }
  ],
  "lastUpdated": "2025-09-22T19:55:37.179Z",
  "overallStatus": "outage"
}