{
  "services": [
    {
      "name": "cloudflare",
      "displayName": "Cloudflare",
      "status": "degraded",
      "description": "Minor Service Outage",
      "lastChecked": "2026-03-20T22:40:24.915Z"
    },
    {
      "name": "azure",
      "displayName": "Azure Services",
      "status": "outage",
      "description": "Major incident affecting multiple services",
      "lastChecked": "2026-03-20T22:40:26.458Z"
    },
    {
      "name": "confluent",
      "displayName": "Confluent Cloud",
      "status": "outage",
      "description": "Partial System Outage",
      "lastChecked": "2026-03-20T22:40:25.149Z"
    },
    {
      "name": "nylas",
      "displayName": "Nylas",
      "status": "operational",
      "description": "No active incidents detected",
      "lastChecked": "2026-03-20T22:40:25.146Z"
    },
    {
      "name": "sendgrid",
      "displayName": "SendGrid",
      "status": "operational",
      "description": "All Systems Operational",
      "lastChecked": "2026-03-20T22:40:25.149Z"
    },
    {
      "name": "twilio",
      "displayName": "Twilio Communications",
      "status": "operational",
      "description": "All Systems Operational",
      "lastChecked": "2026-03-20T22:40:25.240Z"
    },
    {
      "name": "postmark",
      "displayName": "Postmark",
      "status": "operational",
      "description": "All systems operational",
      "lastChecked": "2026-03-20T22:40:25.318Z"
    },
    {
      "name": "zohomail",
      "displayName": "Zoho Mail",
      "status": "operational",
      "description": "All systems operational",
      "lastChecked": "2026-03-20T22:40:26.571Z"
    },
    {
      "name": "mailgun",
      "displayName": "Mailgun",
      "status": "operational",
      "description": "All Systems Operational",
      "lastChecked": "2026-03-20T22:40:25.299Z"
    }
  ],
  "lastUpdated": "2026-03-20T22:40:26.571Z",
  "overallStatus": "outage"
}